pocketflow/__init__.py
pocketflow-0.0.1.dist-info/LICENSE
pocketflow-0.0.1.dist-info/METADATA
pocketflow-0.0.1.dist-info/WHEEL
pocketflow-0.0.1.dist-info/top_level.txt
pocketflow-0.0.1.dist-info/RECORD
